{
  "Name": "DEPTHO_sea_floor_depth",
  "Title": "Sea floor depth below geoid",
  "Description": "The global ocean analysis and forecast system provides 10 days of 3D global ocean forecasts updated daily. The time series is aggregated in time to provide a two-year time series sliding window. The output files are displayed with a 1/12 degree horizontal resolution.",
  "Themes": [
    "Aquaculture",
    "Energy"
  ],
  "CollectionGroup": "J. Bathymetry",
  "DataSource": {
    "Spaceborne": {"Sensor": ""},
    "Other": [
      "Spatial Resolution: 0.083° × 0.083°",
      "Frequency: Static"
    ]
  },
  "Agency": [
    "Mercator Ocean International "
  ],
  "Colorlegend": {
    "title": "Sea floor depth below geoid [m]",
    "range": [
      "rgb(68, 1, 84)",
      "rgb(64, 67, 135)",
      "rgb(41, 120, 142)",
      "rgb(34, 167, 132)",
      "rgb(121, 209, 81)",
      "rgb(253, 231, 36)"
    ],
    "domain": [
      0,
      5727
    ]
  },
  "Citation": {
    "DOI": "10.48670/moi-00016"
  },
  "Resources": [
    {
      "EndPoint": "https://wmts.marine.copernicus.eu/teroWmts/GLOBAL_ANALYSISFORECAST_PHY_001_024/cmems_mod_glo_phy_anfc_0.083deg_static_202211--ext--bathy",
      "Type": "WMTSCapabilities",
      "Name": "marinedatastore",
      "LayerId": "GLOBAL_ANALYSISFORECAST_PHY_001_024/cmems_mod_glo_phy_anfc_0.083deg_static_202211--ext--bathy/deptho",
      "Times": [
          "2022"
      ],
      "Dimensions": {
        "elevation": 0,
        "style": "cmap:viridis"
      }
    }
  ],
"Process": {
    "Name": "process_cmems",
    "JsonForm": "https://raw.githubusercontent.com/gtif-cerulean/assets/refs/heads/main/jsonforms/cmems_jsonform.json",
    "VegaDefinition": "https://raw.githubusercontent.com/gtif-cerulean/assets/refs/heads/main/chartdefs/deptho.json",
    "EndPoints": [
      {
        "Identifier": "process_cmems",
        "Url": "https://cmems.gtif.eox.at/cmems?dataset_id=cmems_mod_glo_bgc-pft_anfc_0.25deg_P1D-m&variables=chl&start_datetime={{date_start}}&end_datetime={{date_end}}&minimum_longitude={{bbox.0}}&minimum_latitude={{bbox.1}}&maximum_longitude={{bbox.2}}&maximum_latitude={{bbox.3}}&minimum_depth={{depth}}&maximum_depth={{depth}}",
        "Type": "application/json"
      }
    ]
  }
}
