{
  "type": "Feature",
  "stac_version": "1.1.0",
  "stac_extensions": [],
  "id": "8ac96549-b3c6-435a-8787-692ace974bd8",
  "geometry": null,
  "properties": {
    "start_datetime": "1970-01-01T00:00:00Z",
    "end_datetime": "2025-02-18T03:43:40.961781Z",
    "datetime": "1970-01-01T00:00:00Z"
  },
  "links": [
    {
      "rel": "root",
      "href": "../../../../catalog.json",
      "type": "application/json",
      "title": "Cerulean GTIF project catalog"
    },
    {
      "rel": "collection",
      "href": "../../collection.json",
      "type": "application/json",
      "title": "Harshness capability"
    },
    {
      "rel": "parent",
      "href": "../../collection.json",
      "type": "application/json",
      "title": "Harshness capability"
    }
  ],
  "assets": {},
  "collection": "harshness"
}