{
  "type": "Catalog",
  "id": "cerulean",
  "stac_version": "1.1.0",
  "description": "Catalog providing description to available datasets to the Cerulean GTIF project",
  "links": [
    {
      "rel": "root",
      "href": "./catalog.json",
      "type": "application/json",
      "title": "Cerulean GTIF project catalog"
    },
    {
      "rel": "child",
      "href": "./coastal_change_monitoring/collection.json",
      "type": "application/json",
      "title": "Coastal Change Monitoring",
      "id": "coastal_change_monitoring",
      "themes": [
        "Shipping",
        "Energy"
      ],
      "satellite": [
        "multiple"
      ],
      "sensor": [
        "multiple"
      ],
      "tags": [
        "processing",
        "capability"
      ],
      "agency": [
        "ESA"
      ],
      "collection_group": "Capabilities"
    },
    {
      "rel": "child",
      "href": "./coastal_change_monitoring_indicator/collection.json",
      "type": "application/json",
      "title": "Coastal Change Monitoring",
      "id": "coastal_change_monitoring_indicator",
      "themes": [
        "Shipping",
        "Energy"
      ],
      "subcode": [
        "SHS1VV"
      ],
      "satellite": [
        "multiple"
      ],
      "sensor": [
        "multiple"
      ],
      "thumbnail": [
        "https://raw.githubusercontent.com/gtif-cerulean/assets/main/collections/Lakes_Sentinel1/thumbnail.png"
      ],
      "tags": [
        "processing",
        "capability"
      ],
      "agency": [
        "ESA"
      ],
      "collection_group": "Capabilities"
    },
    {
      "rel": "self",
      "href": "https://gtif-cerulean.github.io/cerulean-catalog/cerulean/catalog.json",
      "type": "application/json"
    }
  ],
  "title": "Cerulean GTIF project catalog"
}